vkstarti.py
vkstarti-1.5.1.dist-info/WHEEL
vkstarti-1.5.1.dist-info/METADATA
vkstarti-1.5.1.dist-info/RECORD
