Metadata-Version: 2.1
Name: vkstarti
Version: 1.5.1
Summary: 
Author: LooPeKa
Author-email: loudmaks10@gmail.com
Requires-Python: >=3.8,<4.0
Classifier: Programming Language :: Python :: 3
Classifier: Programming Language :: Python :: 3.8
Requires-Dist: colorama (>=0.4.3,<0.5.0)
Requires-Dist: vk_api (>=11.8.0,<12.0.0)
